gradle.properties
hexdoc_hexal/__gradle_version__.py
hexdoc_hexal/__init__.py
hexdoc_hexal/__version__.py
hexdoc_hexal/_hooks.py
hexdoc_hexal/pages.py
hexdoc_hexal/py.typed
hexdoc_hexal/_export/.gitignore
hexdoc_hexal/_export/__init__.py
hexdoc_hexal/_export/generated/__init__.py
hexdoc_hexal/_export/generated/hexal.hexdoc.json
hexdoc_hexal/_export/generated/hexal.patterns.hexdoc.json
hexdoc_hexal/_export/generated/assets/hexal/lang/en_us.json
hexdoc_hexal/_export/generated/assets/hexal/lang/zh_cn.json
hexdoc_hexal/_export/generated/assets/hexal/models/block/relay.json
hexdoc_hexal/_export/generated/assets/hexal/models/item/mediafied_storage.json
hexdoc_hexal/_export/generated/assets/hexal/models/item/relay.json
hexdoc_hexal/_export/generated/assets/hexal/textures/block/empty.png
hexdoc_hexal/_export/generated/assets/hexal/textures/block/mediafied_storage.png
hexdoc_hexal/_export/generated/assets/hexal/textures/block/mythril_block.png
hexdoc_hexal/_export/generated/assets/hexal/textures/block/relay.png
hexdoc_hexal/_export/generated/assets/hexcasting/lang/en_us.flatten.json5
hexdoc_hexal/_export/generated/assets/hexcasting/lang/zh_cn.flatten.json5
hexdoc_hexal/_export/generated/assets/hexcasting/patchouli_books/thehexbook/en_us/entries/basics/slipways.json
hexdoc_hexal/_export/generated/assets/hexcasting/patchouli_books/thehexbook/en_us/entries/interop/fabric_only_hexal.json
hexdoc_hexal/_export/generated/assets/hexcasting/patchouli_books/thehexbook/en_us/entries/items/relay.json
hexdoc_hexal/_export/generated/assets/hexcasting/patchouli_books/thehexbook/en_us/entries/patterns/everbook.json
hexdoc_hexal/_export/generated/assets/hexcasting/patchouli_books/thehexbook/en_us/entries/patterns/everbook_entries.json
hexdoc_hexal/_export/generated/assets/hexcasting/patchouli_books/thehexbook/en_us/entries/patterns/hexal_basics.json
hexdoc_hexal/_export/generated/assets/hexcasting/patchouli_books/thehexbook/en_us/entries/patterns/hexal_maths.json
hexdoc_hexal-0.3.0.1.0.dist-info/METADATA
hexdoc_hexal-0.3.0.1.0.dist-info/WHEEL
hexdoc_hexal-0.3.0.1.0.dist-info/entry_points.txt
hexdoc_hexal-0.3.0.1.0.dist-info/licenses/LICENSE.txt
hexdoc_hexal-0.3.0.1.0.dist-info/RECORD
