Metadata-Version: 2.4
Name: hexdoc-hexal
Version: 0.3.0.1.0
Summary: Python web book docgen and hexdoc plugin for Hexal.
Project-URL: Homepage, https://hexal.hexxy.media
Project-URL: Source, https://github.com/FallingColors/Hexal
Author: FallingColors, Talia-12
License-File: LICENSE.txt
Keywords: hexdoc
Requires-Python: >=3.12
Requires-Dist: hexdoc-hexcasting~=0.11.2.1.0
Requires-Dist: hexdoc-moreiotas~=0.1.1.1.0
